task02/moduloK.v

module ModuloCounter #(parameter k = 16) (
    input clk,           // Takt-Signal
    input reset,         // Reset-Signal
    output reg [31:0] count  // Zählerausgang
);

    always @(posedge clk or posedge reset) begin
        if (reset) begin
            count <= 0;  // Reset: Zähler auf 0 setzen
        end else begin
            if (count == k-1) begin
                count <= 0;  // Wenn der Zähler k-1 erreicht, auf 0 zurücksetzen
            end else begin
                count <= count + 1;  // Zähler inkrementieren
            end
        end
    end
endmodule

task02/testbench2.v
`timescale 1ns/1ps

module testbench();
    reg clk;
    reg reset;
    wire [31:0] count;

    // Instanzierung des Modulo-k-Zählers mit k=16
    ModuloCounter #(16) counter_instance (
        .clk(clk),
        .reset(reset),
        .count(count)
    );

    // Taktgenerator
    always #5 clk = ~clk;  // Takt mit einer Periode von 10 Zeiteinheiten

    initial begin
        // Wellenform-Dump-Dateien erstellen
        $dumpfile("modulo_counter.vcd");
        $dumpvars(0, testbench);

        // Initialisierung
        clk = 0;
        reset = 1;

        // Reset deaktivieren
        #10 reset = 0;

        // Einige Taktzyklen abwarten
        #100;

        // Reset aktivieren und wieder deaktivieren
        #10 reset = 1;
        #10 reset = 0;

        // Weitere Taktzyklen abwarten
        #50;

        // Simulation beenden
        $finish;
    end
endmodule

task02/modulo_counter.vcd
$date
	Wed Aug 21 21:46:44 2024
$end
$version
	Icarus Verilog
$end
$timescale
	1ps
$end
$scope module testbench $end
$var wire 32 ! count [31:0] $end
$var reg 1 " clk $end
$var reg 1 # reset $end
$scope module counter_instance $end
$var wire 1 " clk $end
$var wire 1 # reset $end
$var parameter 32 $ k $end
$var reg 32 % count [31:0] $end
$upscope $end
$upscope $end
$enddefinitions $end
$comment Show the parameter values. $end
$dumpall
b10000 $
$end
#0
$dumpvars
b0 %
1#
0"
b0 !
$end
#5000
1"
#10000
0"
0#
#15000
b1 !
b1 %
1"
#20000
0"
#25000
b10 !
b10 %
1"
#30000
0"
#35000
b11 !
b11 %
1"
#40000
0"
#45000
b100 !
b100 %
1"
#50000
0"
#55000
b101 !
b101 %
1"
#60000
0"
#65000
b110 !
b110 %
1"
#70000
0"
#75000
b111 !
b111 %
1"
#80000
0"
#85000
b1000 !
b1000 %
1"
#90000
0"
#95000
b1001 !
b1001 %
1"
#100000
0"
#105000
b1010 !
b1010 %
1"
#110000
0"
#115000
b1011 !
b1011 %
1"
#120000
b0 !
b0 %
0"
1#
#125000
1"
#130000
0"
0#
#135000
b1 !
b1 %
1"
#140000
0"
#145000
b10 !
b10 %
1"
#150000
0"
#155000
b11 !
b11 %
1"
#160000
0"
#165000
b100 !
b100 %
1"
#170000
0"
#175000
b101 !
b101 %
1"
